{
  "sections": {
    "main": {
      "type": "main-aboutus",
      "blocks": {
        "1349175e-64d8-40a8-889a-dd9ba939cbc8": {
          "type": "title",
          "settings": {
            "title": "Our story"
          }
        },
        "35d4f045-f69d-403c-b1f8-d6f28efc69a2": {
          "type": "featured_image",
          "settings": {
            "image": "shopify:\/\/shop_images\/Rectangle_27.jpg",
            "image_height": "large"
          }
        },
        "1db853b7-1267-4646-b4b7-4d5ed373ca59": {
          "type": "content",
          "settings": {
            "content": "Established in 2016, LARCHIVES is a UK-based online store which specialises in luxury discount shopping. For those who love the thrill of the find, LARCHIVES offers more than 50 of the world’s most prestigious luxury designer fashion brands at exceptional prices of up to 90%off, including Chanel, Hermès, Dior, Louis Vuitton, Gucci, Prada, ChristianLouboutin, and much more. With a dedicated buying team in the UK purchasing stock directly from these leading brands, Larchives helps customers diving into the luxury online shopping \nexperience.\n\nStrong relationships with the brands enables Larchives to build on its key philosophy: keeping the low prices and a sense of responsibility for every purchase, and every experience.With a focus on exceptional customer service, Larchives offers a seamless shoppingexperience across all devices, with worldwide shipping handled with the best of care."
          }
        },
        "cc2333d3-04f4-485c-b7e6-83069cfa7159": {
          "type": "share",
          "settings": {
            "share_label": "Share"
          }
        }
      },
      "block_order": [
        "1349175e-64d8-40a8-889a-dd9ba939cbc8",
        "35d4f045-f69d-403c-b1f8-d6f28efc69a2",
        "1db853b7-1267-4646-b4b7-4d5ed373ca59",
        "cc2333d3-04f4-485c-b7e6-83069cfa7159"
      ],
      "settings": {
      }
    },
    "922f0fb5-4e24-422d-9440-a63fe4c6e070": {
      "type": "instafeed",
      "settings": {
        "heading_size": 20,
        "feed_width": 100,
        "html_area": ""
      }
    }
  },
  "order": [
    "main",
    "922f0fb5-4e24-422d-9440-a63fe4c6e070"
  ]
}
